README.md
setup.py
bmitzkus_pulumi_onepassword/__init__.py
bmitzkus_pulumi_onepassword/_inputs.py
bmitzkus_pulumi_onepassword/_utilities.py
bmitzkus_pulumi_onepassword/get_item.py
bmitzkus_pulumi_onepassword/get_vault.py
bmitzkus_pulumi_onepassword/item.py
bmitzkus_pulumi_onepassword/outputs.py
bmitzkus_pulumi_onepassword/provider.py
bmitzkus_pulumi_onepassword/pulumi-plugin.json
bmitzkus_pulumi_onepassword/py.typed
bmitzkus_pulumi_onepassword.egg-info/PKG-INFO
bmitzkus_pulumi_onepassword.egg-info/SOURCES.txt
bmitzkus_pulumi_onepassword.egg-info/dependency_links.txt
bmitzkus_pulumi_onepassword.egg-info/not-zip-safe
bmitzkus_pulumi_onepassword.egg-info/requires.txt
bmitzkus_pulumi_onepassword.egg-info/top_level.txt
bmitzkus_pulumi_onepassword/config/__init__.py
bmitzkus_pulumi_onepassword/config/vars.py