Metadata-Version: 2.1
Name: bmitzkus-pulumi-onepassword
Version: 0.0.15
Summary: A Pulumi package for creating and managing onepassword cloud resources.
Home-page: https://www.pulumi.com
License: Apache-2.0
Project-URL: Repository, https://github.com/Hvitgar/pulumi-onepassword
Keywords: pulumi onepassword category/cloud
Platform: UNKNOWN
Requires-Python: >=3.7
